{"nodes": [{"id": "c_users_15anu_onedrive_code_ecomm_aarya_clothing_services_admin_service_excel_service_py", "label": "excel_service.py", "file_type": "code", "source_file": "C:\\Users\\15anu\\OneDrive\\\u6587\u6863\\code\\ecomm\\Aarya_Clothing\\services\\admin\\service\\excel_service.py", "source_location": "L1"}, {"id": "excel_service_autosize", "label": "_autosize()", "file_type": "code", "source_file": "C:\\Users\\15anu\\OneDrive\\\u6587\u6863\\code\\ecomm\\Aarya_Clothing\\services\\admin\\service\\excel_service.py", "source_location": "L22"}, {"id": "excel_service_write_sheet", "label": "_write_sheet()", "file_type": "code", "source_file": "C:\\Users\\15anu\\OneDrive\\\u6587\u6863\\code\\ecomm\\Aarya_Clothing\\services\\admin\\service\\excel_service.py", "source_location": "L33"}, {"id": "excel_service_wb_to_bytes", "label": "_wb_to_bytes()", "file_type": "code", "source_file": "C:\\Users\\15anu\\OneDrive\\\u6587\u6863\\code\\ecomm\\Aarya_Clothing\\services\\admin\\service\\excel_service.py", "source_location": "L40"}, {"id": "excel_service_export_products", "label": "export_products()", "file_type": "code", "source_file": "C:\\Users\\15anu\\OneDrive\\\u6587\u6863\\code\\ecomm\\Aarya_Clothing\\services\\admin\\service\\excel_service.py", "source_location": "L72"}, {"id": "excel_service_parse_products_import", "label": "parse_products_import()", "file_type": "code", "source_file": "C:\\Users\\15anu\\OneDrive\\\u6587\u6863\\code\\ecomm\\Aarya_Clothing\\services\\admin\\service\\excel_service.py", "source_location": "L90"}, {"id": "excel_service_products_template", "label": "products_template()", "file_type": "code", "source_file": "C:\\Users\\15anu\\OneDrive\\\u6587\u6863\\code\\ecomm\\Aarya_Clothing\\services\\admin\\service\\excel_service.py", "source_location": "L111"}, {"id": "excel_service_export_orders", "label": "export_orders()", "file_type": "code", "source_file": "C:\\Users\\15anu\\OneDrive\\\u6587\u6863\\code\\ecomm\\Aarya_Clothing\\services\\admin\\service\\excel_service.py", "source_location": "L153"}, {"id": "excel_service_export_inventory", "label": "export_inventory()", "file_type": "code", "source_file": "C:\\Users\\15anu\\OneDrive\\\u6587\u6863\\code\\ecomm\\Aarya_Clothing\\services\\admin\\service\\excel_service.py", "source_location": "L185"}, {"id": "excel_service_inventory_template", "label": "inventory_template()", "file_type": "code", "source_file": "C:\\Users\\15anu\\OneDrive\\\u6587\u6863\\code\\ecomm\\Aarya_Clothing\\services\\admin\\service\\excel_service.py", "source_location": "L197"}, {"id": "excel_service_parse_inventory_import", "label": "parse_inventory_import()", "file_type": "code", "source_file": "C:\\Users\\15anu\\OneDrive\\\u6587\u6863\\code\\ecomm\\Aarya_Clothing\\services\\admin\\service\\excel_service.py", "source_location": "L207"}, {"id": "excel_service_rationale_1", "label": "Excel import/export utilities for the admin service.  Uses openpyxl. Provides", "file_type": "rationale", "source_file": "C:\\Users\\15anu\\OneDrive\\\u6587\u6863\\code\\ecomm\\Aarya_Clothing\\services\\admin\\service\\excel_service.py", "source_location": "L1"}, {"id": "excel_service_rationale_23", "label": "Best-effort autosize; openpyxl can't measure exactly so we cap.", "file_type": "rationale", "source_file": "C:\\Users\\15anu\\OneDrive\\\u6587\u6863\\code\\ecomm\\Aarya_Clothing\\services\\admin\\service\\excel_service.py", "source_location": "L23"}, {"id": "excel_service_rationale_73", "label": "Flatten products + variants to one row per variant.      `rows` is the raw joi", "file_type": "rationale", "source_file": "C:\\Users\\15anu\\OneDrive\\\u6587\u6863\\code\\ecomm\\Aarya_Clothing\\services\\admin\\service\\excel_service.py", "source_location": "L73"}, {"id": "excel_service_rationale_91", "label": "Parse an uploaded products workbook back into row dicts.      Validates that a", "file_type": "rationale", "source_file": "C:\\Users\\15anu\\OneDrive\\\u6587\u6863\\code\\ecomm\\Aarya_Clothing\\services\\admin\\service\\excel_service.py", "source_location": "L91"}, {"id": "excel_service_rationale_208", "label": "Parse an inventory workbook keyed by SKU. Used for bulk stock updates.", "file_type": "rationale", "source_file": "C:\\Users\\15anu\\OneDrive\\\u6587\u6863\\code\\ecomm\\Aarya_Clothing\\services\\admin\\service\\excel_service.py", "source_location": "L208"}], "edges": [{"source": "c_users_15anu_onedrive_code_ecomm_aarya_clothing_services_admin_service_excel_service_py", "target": "io", "relation": "imports", "confidence": "EXTRACTED", "source_file": "C:\\Users\\15anu\\OneDrive\\\u6587\u6863\\code\\ecomm\\Aarya_Clothing\\services\\admin\\service\\excel_service.py", "source_location": "L11", "weight": 1.0}, {"source": "c_users_15anu_onedrive_code_ecomm_aarya_clothing_services_admin_service_excel_service_py", "target": "typing", "relation": "imports_from", "confidence": "EXTRACTED", "source_file": "C:\\Users\\15anu\\OneDrive\\\u6587\u6863\\code\\ecomm\\Aarya_Clothing\\services\\admin\\service\\excel_service.py", "source_location": "L12", "weight": 1.0}, {"source": "c_users_15anu_onedrive_code_ecomm_aarya_clothing_services_admin_service_excel_service_py", "target": "openpyxl", "relation": "imports_from", "confidence": "EXTRACTED", "source_file": "C:\\Users\\15anu\\OneDrive\\\u6587\u6863\\code\\ecomm\\Aarya_Clothing\\services\\admin\\service\\excel_service.py", "source_location": "L14", "weight": 1.0}, {"source": "c_users_15anu_onedrive_code_ecomm_aarya_clothing_services_admin_service_excel_service_py", "target": "openpyxl_utils", "relation": "imports_from", "confidence": "EXTRACTED", "source_file": "C:\\Users\\15anu\\OneDrive\\\u6587\u6863\\code\\ecomm\\Aarya_Clothing\\services\\admin\\service\\excel_service.py", "source_location": "L15", "weight": 1.0}, {"source": "c_users_15anu_onedrive_code_ecomm_aarya_clothing_services_admin_service_excel_service_py", "target": "excel_service_autosize", "relation": "contains", "confidence": "EXTRACTED", "source_file": "C:\\Users\\15anu\\OneDrive\\\u6587\u6863\\code\\ecomm\\Aarya_Clothing\\services\\admin\\service\\excel_service.py", "source_location": "L22", "weight": 1.0}, {"source": "c_users_15anu_onedrive_code_ecomm_aarya_clothing_services_admin_service_excel_service_py", "target": "excel_service_write_sheet", "relation": "contains", "confidence": "EXTRACTED", "source_file": "C:\\Users\\15anu\\OneDrive\\\u6587\u6863\\code\\ecomm\\Aarya_Clothing\\services\\admin\\service\\excel_service.py", "source_location": "L33", "weight": 1.0}, {"source": "c_users_15anu_onedrive_code_ecomm_aarya_clothing_services_admin_service_excel_service_py", "target": "excel_service_wb_to_bytes", "relation": "contains", "confidence": "EXTRACTED", "source_file": "C:\\Users\\15anu\\OneDrive\\\u6587\u6863\\code\\ecomm\\Aarya_Clothing\\services\\admin\\service\\excel_service.py", "source_location": "L40", "weight": 1.0}, {"source": "c_users_15anu_onedrive_code_ecomm_aarya_clothing_services_admin_service_excel_service_py", "target": "excel_service_export_products", "relation": "contains", "confidence": "EXTRACTED", "source_file": "C:\\Users\\15anu\\OneDrive\\\u6587\u6863\\code\\ecomm\\Aarya_Clothing\\services\\admin\\service\\excel_service.py", "source_location": "L72", "weight": 1.0}, {"source": "c_users_15anu_onedrive_code_ecomm_aarya_clothing_services_admin_service_excel_service_py", "target": "excel_service_parse_products_import", "relation": "contains", "confidence": "EXTRACTED", "source_file": "C:\\Users\\15anu\\OneDrive\\\u6587\u6863\\code\\ecomm\\Aarya_Clothing\\services\\admin\\service\\excel_service.py", "source_location": "L90", "weight": 1.0}, {"source": "c_users_15anu_onedrive_code_ecomm_aarya_clothing_services_admin_service_excel_service_py", "target": "excel_service_products_template", "relation": "contains", "confidence": "EXTRACTED", "source_file": "C:\\Users\\15anu\\OneDrive\\\u6587\u6863\\code\\ecomm\\Aarya_Clothing\\services\\admin\\service\\excel_service.py", "source_location": "L111", "weight": 1.0}, {"source": "c_users_15anu_onedrive_code_ecomm_aarya_clothing_services_admin_service_excel_service_py", "target": "excel_service_export_orders", "relation": "contains", "confidence": "EXTRACTED", "source_file": "C:\\Users\\15anu\\OneDrive\\\u6587\u6863\\code\\ecomm\\Aarya_Clothing\\services\\admin\\service\\excel_service.py", "source_location": "L153", "weight": 1.0}, {"source": "c_users_15anu_onedrive_code_ecomm_aarya_clothing_services_admin_service_excel_service_py", "target": "excel_service_export_inventory", "relation": "contains", "confidence": "EXTRACTED", "source_file": "C:\\Users\\15anu\\OneDrive\\\u6587\u6863\\code\\ecomm\\Aarya_Clothing\\services\\admin\\service\\excel_service.py", "source_location": "L185", "weight": 1.0}, {"source": "c_users_15anu_onedrive_code_ecomm_aarya_clothing_services_admin_service_excel_service_py", "target": "excel_service_inventory_template", "relation": "contains", "confidence": "EXTRACTED", "source_file": "C:\\Users\\15anu\\OneDrive\\\u6587\u6863\\code\\ecomm\\Aarya_Clothing\\services\\admin\\service\\excel_service.py", "source_location": "L197", "weight": 1.0}, {"source": "c_users_15anu_onedrive_code_ecomm_aarya_clothing_services_admin_service_excel_service_py", "target": "excel_service_parse_inventory_import", "relation": "contains", "confidence": "EXTRACTED", "source_file": "C:\\Users\\15anu\\OneDrive\\\u6587\u6863\\code\\ecomm\\Aarya_Clothing\\services\\admin\\service\\excel_service.py", "source_location": "L207", "weight": 1.0}, {"source": "excel_service_write_sheet", "target": "excel_service_autosize", "relation": "calls", "confidence": "EXTRACTED", "source_file": "C:\\Users\\15anu\\OneDrive\\\u6587\u6863\\code\\ecomm\\Aarya_Clothing\\services\\admin\\service\\excel_service.py", "source_location": "L37", "weight": 1.0}, {"source": "excel_service_export_products", "target": "excel_service_write_sheet", "relation": "calls", "confidence": "EXTRACTED", "source_file": "C:\\Users\\15anu\\OneDrive\\\u6587\u6863\\code\\ecomm\\Aarya_Clothing\\services\\admin\\service\\excel_service.py", "source_location": "L82", "weight": 1.0}, {"source": "excel_service_export_products", "target": "excel_service_wb_to_bytes", "relation": "calls", "confidence": "EXTRACTED", "source_file": "C:\\Users\\15anu\\OneDrive\\\u6587\u6863\\code\\ecomm\\Aarya_Clothing\\services\\admin\\service\\excel_service.py", "source_location": "L87", "weight": 1.0}, {"source": "excel_service_products_template", "target": "excel_service_autosize", "relation": "calls", "confidence": "EXTRACTED", "source_file": "C:\\Users\\15anu\\OneDrive\\\u6587\u6863\\code\\ecomm\\Aarya_Clothing\\services\\admin\\service\\excel_service.py", "source_location": "L123", "weight": 1.0}, {"source": "excel_service_products_template", "target": "excel_service_wb_to_bytes", "relation": "calls", "confidence": "EXTRACTED", "source_file": "C:\\Users\\15anu\\OneDrive\\\u6587\u6863\\code\\ecomm\\Aarya_Clothing\\services\\admin\\service\\excel_service.py", "source_location": "L124", "weight": 1.0}, {"source": "excel_service_export_orders", "target": "excel_service_write_sheet", "relation": "calls", "confidence": "EXTRACTED", "source_file": "C:\\Users\\15anu\\OneDrive\\\u6587\u6863\\code\\ecomm\\Aarya_Clothing\\services\\admin\\service\\excel_service.py", "source_location": "L157", "weight": 1.0}, {"source": "excel_service_export_orders", "target": "excel_service_wb_to_bytes", "relation": "calls", "confidence": "EXTRACTED", "source_file": "C:\\Users\\15anu\\OneDrive\\\u6587\u6863\\code\\ecomm\\Aarya_Clothing\\services\\admin\\service\\excel_service.py", "source_location": "L162", "weight": 1.0}, {"source": "excel_service_export_inventory", "target": "excel_service_write_sheet", "relation": "calls", "confidence": "EXTRACTED", "source_file": "C:\\Users\\15anu\\OneDrive\\\u6587\u6863\\code\\ecomm\\Aarya_Clothing\\services\\admin\\service\\excel_service.py", "source_location": "L189", "weight": 1.0}, {"source": "excel_service_export_inventory", "target": "excel_service_wb_to_bytes", "relation": "calls", "confidence": "EXTRACTED", "source_file": "C:\\Users\\15anu\\OneDrive\\\u6587\u6863\\code\\ecomm\\Aarya_Clothing\\services\\admin\\service\\excel_service.py", "source_location": "L194", "weight": 1.0}, {"source": "excel_service_inventory_template", "target": "excel_service_autosize", "relation": "calls", "confidence": "EXTRACTED", "source_file": "C:\\Users\\15anu\\OneDrive\\\u6587\u6863\\code\\ecomm\\Aarya_Clothing\\services\\admin\\service\\excel_service.py", "source_location": "L203", "weight": 1.0}, {"source": "excel_service_inventory_template", "target": "excel_service_wb_to_bytes", "relation": "calls", "confidence": "EXTRACTED", "source_file": "C:\\Users\\15anu\\OneDrive\\\u6587\u6863\\code\\ecomm\\Aarya_Clothing\\services\\admin\\service\\excel_service.py", "source_location": "L204", "weight": 1.0}, {"source": "excel_service_rationale_1", "target": "c_users_15anu_onedrive_code_ecomm_aarya_clothing_services_admin_service_excel_service_py", "relation": "rationale_for", "confidence": "EXTRACTED", "source_file": "C:\\Users\\15anu\\OneDrive\\\u6587\u6863\\code\\ecomm\\Aarya_Clothing\\services\\admin\\service\\excel_service.py", "source_location": "L1", "weight": 1.0}, {"source": "excel_service_rationale_23", "target": "excel_service_autosize", "relation": "rationale_for", "confidence": "EXTRACTED", "source_file": "C:\\Users\\15anu\\OneDrive\\\u6587\u6863\\code\\ecomm\\Aarya_Clothing\\services\\admin\\service\\excel_service.py", "source_location": "L23", "weight": 1.0}, {"source": "excel_service_rationale_73", "target": "excel_service_export_products", "relation": "rationale_for", "confidence": "EXTRACTED", "source_file": "C:\\Users\\15anu\\OneDrive\\\u6587\u6863\\code\\ecomm\\Aarya_Clothing\\services\\admin\\service\\excel_service.py", "source_location": "L73", "weight": 1.0}, {"source": "excel_service_rationale_91", "target": "excel_service_parse_products_import", "relation": "rationale_for", "confidence": "EXTRACTED", "source_file": "C:\\Users\\15anu\\OneDrive\\\u6587\u6863\\code\\ecomm\\Aarya_Clothing\\services\\admin\\service\\excel_service.py", "source_location": "L91", "weight": 1.0}, {"source": "excel_service_rationale_208", "target": "excel_service_parse_inventory_import", "relation": "rationale_for", "confidence": "EXTRACTED", "source_file": "C:\\Users\\15anu\\OneDrive\\\u6587\u6863\\code\\ecomm\\Aarya_Clothing\\services\\admin\\service\\excel_service.py", "source_location": "L208", "weight": 1.0}], "raw_calls": [{"caller_nid": "excel_service_autosize", "callee": "enumerate", "source_file": "C:\\Users\\15anu\\OneDrive\\\u6587\u6863\\code\\ecomm\\Aarya_Clothing\\services\\admin\\service\\excel_service.py", "source_location": "L24"}, {"caller_nid": "excel_service_autosize", "callee": "str", "source_file": "C:\\Users\\15anu\\OneDrive\\\u6587\u6863\\code\\ecomm\\Aarya_Clothing\\services\\admin\\service\\excel_service.py", "source_location": "L27"}, {"caller_nid": "excel_service_autosize", "callee": "len", "source_file": "C:\\Users\\15anu\\OneDrive\\\u6587\u6863\\code\\ecomm\\Aarya_Clothing\\services\\admin\\service\\excel_service.py", "source_location": "L28"}, {"caller_nid": "excel_service_autosize", "callee": "min", "source_file": "C:\\Users\\15anu\\OneDrive\\\u6587\u6863\\code\\ecomm\\Aarya_Clothing\\services\\admin\\service\\excel_service.py", "source_location": "L29"}, {"caller_nid": "excel_service_autosize", "callee": "len", "source_file": "C:\\Users\\15anu\\OneDrive\\\u6587\u6863\\code\\ecomm\\Aarya_Clothing\\services\\admin\\service\\excel_service.py", "source_location": "L29"}, {"caller_nid": "excel_service_autosize", "callee": "get_column_letter", "source_file": "C:\\Users\\15anu\\OneDrive\\\u6587\u6863\\code\\ecomm\\Aarya_Clothing\\services\\admin\\service\\excel_service.py", "source_location": "L30"}, {"caller_nid": "excel_service_autosize", "callee": "max", "source_file": "C:\\Users\\15anu\\OneDrive\\\u6587\u6863\\code\\ecomm\\Aarya_Clothing\\services\\admin\\service\\excel_service.py", "source_location": "L30"}, {"caller_nid": "excel_service_write_sheet", "callee": "append", "source_file": "C:\\Users\\15anu\\OneDrive\\\u6587\u6863\\code\\ecomm\\Aarya_Clothing\\services\\admin\\service\\excel_service.py", "source_location": "L34"}, {"caller_nid": "excel_service_write_sheet", "callee": "append", "source_file": "C:\\Users\\15anu\\OneDrive\\\u6587\u6863\\code\\ecomm\\Aarya_Clothing\\services\\admin\\service\\excel_service.py", "source_location": "L36"}, {"caller_nid": "excel_service_write_sheet", "callee": "list", "source_file": "C:\\Users\\15anu\\OneDrive\\\u6587\u6863\\code\\ecomm\\Aarya_Clothing\\services\\admin\\service\\excel_service.py", "source_location": "L36"}, {"caller_nid": "excel_service_wb_to_bytes", "callee": "BytesIO", "source_file": "C:\\Users\\15anu\\OneDrive\\\u6587\u6863\\code\\ecomm\\Aarya_Clothing\\services\\admin\\service\\excel_service.py", "source_location": "L41"}, {"caller_nid": "excel_service_wb_to_bytes", "callee": "save", "source_file": "C:\\Users\\15anu\\OneDrive\\\u6587\u6863\\code\\ecomm\\Aarya_Clothing\\services\\admin\\service\\excel_service.py", "source_location": "L42"}, {"caller_nid": "excel_service_wb_to_bytes", "callee": "seek", "source_file": "C:\\Users\\15anu\\OneDrive\\\u6587\u6863\\code\\ecomm\\Aarya_Clothing\\services\\admin\\service\\excel_service.py", "source_location": "L43"}, {"caller_nid": "excel_service_wb_to_bytes", "callee": "read", "source_file": "C:\\Users\\15anu\\OneDrive\\\u6587\u6863\\code\\ecomm\\Aarya_Clothing\\services\\admin\\service\\excel_service.py", "source_location": "L44"}, {"caller_nid": "excel_service_export_products", "callee": "Workbook", "source_file": "C:\\Users\\15anu\\OneDrive\\\u6587\u6863\\code\\ecomm\\Aarya_Clothing\\services\\admin\\service\\excel_service.py", "source_location": "L79"}, {"caller_nid": "excel_service_export_products", "callee": "get", "source_file": "C:\\Users\\15anu\\OneDrive\\\u6587\u6863\\code\\ecomm\\Aarya_Clothing\\services\\admin\\service\\excel_service.py", "source_location": "L85"}, {"caller_nid": "excel_service_parse_products_import", "callee": "load_workbook", "source_file": "C:\\Users\\15anu\\OneDrive\\\u6587\u6863\\code\\ecomm\\Aarya_Clothing\\services\\admin\\service\\excel_service.py", "source_location": "L97"}, {"caller_nid": "excel_service_parse_products_import", "callee": "BytesIO", "source_file": "C:\\Users\\15anu\\OneDrive\\\u6587\u6863\\code\\ecomm\\Aarya_Clothing\\services\\admin\\service\\excel_service.py", "source_location": "L97"}, {"caller_nid": "excel_service_parse_products_import", "callee": "next", "source_file": "C:\\Users\\15anu\\OneDrive\\\u6587\u6863\\code\\ecomm\\Aarya_Clothing\\services\\admin\\service\\excel_service.py", "source_location": "L99"}, {"caller_nid": "excel_service_parse_products_import", "callee": "iter_rows", "source_file": "C:\\Users\\15anu\\OneDrive\\\u6587\u6863\\code\\ecomm\\Aarya_Clothing\\services\\admin\\service\\excel_service.py", "source_location": "L99"}, {"caller_nid": "excel_service_parse_products_import", "callee": "ValueError", "source_file": "C:\\Users\\15anu\\OneDrive\\\u6587\u6863\\code\\ecomm\\Aarya_Clothing\\services\\admin\\service\\excel_service.py", "source_location": "L102"}, {"caller_nid": "excel_service_parse_products_import", "callee": "join", "source_file": "C:\\Users\\15anu\\OneDrive\\\u6587\u6863\\code\\ecomm\\Aarya_Clothing\\services\\admin\\service\\excel_service.py", "source_location": "L102"}, {"caller_nid": "excel_service_parse_products_import", "callee": "iter_rows", "source_file": "C:\\Users\\15anu\\OneDrive\\\u6587\u6863\\code\\ecomm\\Aarya_Clothing\\services\\admin\\service\\excel_service.py", "source_location": "L104"}, {"caller_nid": "excel_service_parse_products_import", "callee": "all", "source_file": "C:\\Users\\15anu\\OneDrive\\\u6587\u6863\\code\\ecomm\\Aarya_Clothing\\services\\admin\\service\\excel_service.py", "source_location": "L105"}, {"caller_nid": "excel_service_parse_products_import", "callee": "append", "source_file": "C:\\Users\\15anu\\OneDrive\\\u6587\u6863\\code\\ecomm\\Aarya_Clothing\\services\\admin\\service\\excel_service.py", "source_location": "L107"}, {"caller_nid": "excel_service_parse_products_import", "callee": "dict", "source_file": "C:\\Users\\15anu\\OneDrive\\\u6587\u6863\\code\\ecomm\\Aarya_Clothing\\services\\admin\\service\\excel_service.py", "source_location": "L107"}, {"caller_nid": "excel_service_parse_products_import", "callee": "zip", "source_file": "C:\\Users\\15anu\\OneDrive\\\u6587\u6863\\code\\ecomm\\Aarya_Clothing\\services\\admin\\service\\excel_service.py", "source_location": "L107"}, {"caller_nid": "excel_service_products_template", "callee": "Workbook", "source_file": "C:\\Users\\15anu\\OneDrive\\\u6587\u6863\\code\\ecomm\\Aarya_Clothing\\services\\admin\\service\\excel_service.py", "source_location": "L112"}, {"caller_nid": "excel_service_products_template", "callee": "append", "source_file": "C:\\Users\\15anu\\OneDrive\\\u6587\u6863\\code\\ecomm\\Aarya_Clothing\\services\\admin\\service\\excel_service.py", "source_location": "L115"}, {"caller_nid": "excel_service_products_template", "callee": "append", "source_file": "C:\\Users\\15anu\\OneDrive\\\u6587\u6863\\code\\ecomm\\Aarya_Clothing\\services\\admin\\service\\excel_service.py", "source_location": "L122"}, {"caller_nid": "excel_service_export_orders", "callee": "Workbook", "source_file": "C:\\Users\\15anu\\OneDrive\\\u6587\u6863\\code\\ecomm\\Aarya_Clothing\\services\\admin\\service\\excel_service.py", "source_location": "L154"}, {"caller_nid": "excel_service_export_orders", "callee": "get", "source_file": "C:\\Users\\15anu\\OneDrive\\\u6587\u6863\\code\\ecomm\\Aarya_Clothing\\services\\admin\\service\\excel_service.py", "source_location": "L160"}, {"caller_nid": "excel_service_export_inventory", "callee": "Workbook", "source_file": "C:\\Users\\15anu\\OneDrive\\\u6587\u6863\\code\\ecomm\\Aarya_Clothing\\services\\admin\\service\\excel_service.py", "source_location": "L186"}, {"caller_nid": "excel_service_export_inventory", "callee": "get", "source_file": "C:\\Users\\15anu\\OneDrive\\\u6587\u6863\\code\\ecomm\\Aarya_Clothing\\services\\admin\\service\\excel_service.py", "source_location": "L192"}, {"caller_nid": "excel_service_inventory_template", "callee": "Workbook", "source_file": "C:\\Users\\15anu\\OneDrive\\\u6587\u6863\\code\\ecomm\\Aarya_Clothing\\services\\admin\\service\\excel_service.py", "source_location": "L198"}, {"caller_nid": "excel_service_inventory_template", "callee": "append", "source_file": "C:\\Users\\15anu\\OneDrive\\\u6587\u6863\\code\\ecomm\\Aarya_Clothing\\services\\admin\\service\\excel_service.py", "source_location": "L201"}, {"caller_nid": "excel_service_inventory_template", "callee": "append", "source_file": "C:\\Users\\15anu\\OneDrive\\\u6587\u6863\\code\\ecomm\\Aarya_Clothing\\services\\admin\\service\\excel_service.py", "source_location": "L202"}, {"caller_nid": "excel_service_parse_inventory_import", "callee": "load_workbook", "source_file": "C:\\Users\\15anu\\OneDrive\\\u6587\u6863\\code\\ecomm\\Aarya_Clothing\\services\\admin\\service\\excel_service.py", "source_location": "L209"}, {"caller_nid": "excel_service_parse_inventory_import", "callee": "BytesIO", "source_file": "C:\\Users\\15anu\\OneDrive\\\u6587\u6863\\code\\ecomm\\Aarya_Clothing\\services\\admin\\service\\excel_service.py", "source_location": "L209"}, {"caller_nid": "excel_service_parse_inventory_import", "callee": "next", "source_file": "C:\\Users\\15anu\\OneDrive\\\u6587\u6863\\code\\ecomm\\Aarya_Clothing\\services\\admin\\service\\excel_service.py", "source_location": "L211"}, {"caller_nid": "excel_service_parse_inventory_import", "callee": "iter_rows", "source_file": "C:\\Users\\15anu\\OneDrive\\\u6587\u6863\\code\\ecomm\\Aarya_Clothing\\services\\admin\\service\\excel_service.py", "source_location": "L211"}, {"caller_nid": "excel_service_parse_inventory_import", "callee": "ValueError", "source_file": "C:\\Users\\15anu\\OneDrive\\\u6587\u6863\\code\\ecomm\\Aarya_Clothing\\services\\admin\\service\\excel_service.py", "source_location": "L213"}, {"caller_nid": "excel_service_parse_inventory_import", "callee": "iter_rows", "source_file": "C:\\Users\\15anu\\OneDrive\\\u6587\u6863\\code\\ecomm\\Aarya_Clothing\\services\\admin\\service\\excel_service.py", "source_location": "L215"}, {"caller_nid": "excel_service_parse_inventory_import", "callee": "all", "source_file": "C:\\Users\\15anu\\OneDrive\\\u6587\u6863\\code\\ecomm\\Aarya_Clothing\\services\\admin\\service\\excel_service.py", "source_location": "L216"}, {"caller_nid": "excel_service_parse_inventory_import", "callee": "append", "source_file": "C:\\Users\\15anu\\OneDrive\\\u6587\u6863\\code\\ecomm\\Aarya_Clothing\\services\\admin\\service\\excel_service.py", "source_location": "L218"}, {"caller_nid": "excel_service_parse_inventory_import", "callee": "dict", "source_file": "C:\\Users\\15anu\\OneDrive\\\u6587\u6863\\code\\ecomm\\Aarya_Clothing\\services\\admin\\service\\excel_service.py", "source_location": "L218"}, {"caller_nid": "excel_service_parse_inventory_import", "callee": "zip", "source_file": "C:\\Users\\15anu\\OneDrive\\\u6587\u6863\\code\\ecomm\\Aarya_Clothing\\services\\admin\\service\\excel_service.py", "source_location": "L218"}]}